{"inkVersion":21,"root":[[{"->":"loremaster"},["done",{"#f":5,"#n":"g-0"}],null],"done",{"loremaster":[["^You smell her first, on the wind. Human smells. Sweat. Smoke. Fat. <i>Rancid</i>. ","#","^narration","/#","\n","ev","str","^Watch him approach","/str","/ev",{"*":".^.c-0","flg":20},{"c-0":["\n",{"->":".^.^.^.loremaster_approach"},{"#f":5}]}],{"loremaster_approach":[["^Footsteps, clumsy on rock and sand. Horrible ungainly creature. <i>Closer, closer, come into the water</i>.","\n","^But the song is done. Your voice is gone. She stops when the surf washes over her boots and looks at you. Then shifts her gaze to the village above. ","#","^narration","/#","\n","ev","str","^Watch her warily","/str","/ev",{"*":".^.c-0","flg":20},{"c-0":["\n",{"->":".^.^.^.^.loremaster_reflects"},{"#f":5}]}],{"#f":1}],"loremaster_reflects":[["^\"It's all beautiful, isn't it? Our home. Our people.\" ","#","^loremaster","/#","\n","ev","str","^Stare at her","/str","/ev",{"*":".^.c-0","flg":20},{"c-0":["\n",{"->":".^.^.^.^.siren_stares"},{"#f":5}]}],{"#f":1}],"siren_stares":[["^The hunger claws at your own belly. The crabs and silver fishes sustain you, but it's never enough. The hole inside is always there. Seeing her, it grows deeper.","\n","^Come into the water. <i>Come into the water. <b>Come into the water.</b></i>","\n","^She glances back at you. ","#","^narration","/#","\n","ev","str","^Continue staring","/str","/ev",{"*":".^.c-0","flg":20},{"c-0":["\n",{"->":".^.^.^.^.loremaster_beauty"},{"#f":5}]}],{"#f":1}],"loremaster_beauty":[["^\"Well, perhaps not everything can be beautiful. But the town is flourishing now. Thanks to you. To me.\"  ","#","^loremaster","/#","\n","ev","str","^Glare at her","/str","/ev",{"*":".^.c-0","flg":20},"ev","str","^Look away","/str","/ev",{"*":".^.c-1","flg":20},{"c-0":["\n",{"->":".^.^.^.^.loremaster_praise"},{"#f":5}],"c-1":["\n",{"->":".^.^.^.^.loremaster_bashful"},{"#f":5}]}],{"#f":1}],"loremaster_bashful":["^\"Now now, don't be bashful.\" A pause. ","<>","^ ","#","^loremaster","/#","\n",{"->":".^.^.loremaster_praise"},{"#f":1}],"loremaster_praise":[["^\"I mean it. Truly, I do. This is our doing. Without you, our people would have starved. Our homes would have collapsed. And without me, well... ","#","^loremaster","/#","\n","ev","str","^Stare at her","/str","/ev",{"*":".^.c-0","flg":20},"ev","str","^Show your sharp teeth","/str","/ev",{"*":".^.c-1","flg":20},{"c-0":["\n","^\"Let's ","<>","^ ","#","^loremaster","/#","\n",{"->":".^.^.g-0"},{"#f":5}],"c-1":["\n","^\"And without her too, of course. You're absolutely correct. Ultimately it's all her doing. But let's ","<>","^ ","#","^loremaster","/#","\n",{"->":".^.^.g-0"},{"#f":5}],"g-0":["^just say the future looks bright now. The old ways are best way forward.\" ","#","^loremaster","/#","\n",{"->":"loremaster_choice"},{"#f":5}]}],{"#f":1}],"#f":1}],"loremaster_choice":[["ev","str","^Bare your teeth at her","/str",{"VAR?":"teeth_done"},false,"==","/ev",{"*":".^.c-0","flg":21},"ev","str","^Look away","/str",{"VAR?":"away_done"},false,"==","/ev",{"*":".^.c-1","flg":21},"ev","str","^Sing","/str",{"VAR?":"teeth_done"},true,"==",{"VAR?":"away_done"},true,"==","&&","/ev",{"*":".^.c-2","flg":21},{"c-0":["^ ","\n",{"->":".^.^.^.siren_lore_teeth"},{"#f":5}],"c-1":["^ ","\n",{"->":".^.^.^.siren_lore_away"},{"#f":5}],"c-2":["^ ","\n",{"->":"loremaster_song"},{"#f":5}]}],{"siren_lore_teeth":[["^Her blood would be hot and red, like a porpoise. Sickly, though, like the other ones, from the outside, who come when you call. ","#","^narrator","/#","\n","ev","str","^Next","/str","/ev",{"*":".^.c-0","flg":20},{"c-0":["\n",{"->":".^.^.^.^.lorekeeper_enthused"},{"#f":5}]}],{"#f":1}],"lorekeeper_enthused":["ev",true,"/ev",{"VAR=":"teeth_done","re":true},"^\"Yes! Exactly! The outsiders' blood will water our lands and their machines refresh the bones of our town.\" ","#","^loremaster","/#","\n",{"->":".^.^"},{"#f":1}],"siren_lore_away":[["^A new scent on the night wind. Warm. Clean. Familiar. And then gone. ","#","^narrator","/#","\n","ev","str","^Look back at the human","/str","/ev",{"*":".^.c-0","flg":20},{"c-0":["\n",{"->":".^.^.^.^.loremaster_bones"},{"#f":5}]}],{"#f":1}],"loremaster_bones":["ev",true,"/ev",{"VAR=":"away_done","re":true},"^\"You know it's true. You must feel it in your bones now.\" ","#","^loremaster","/#","\n",{"->":".^.^"},{"#f":1}],"#f":1}],"loremaster_song":[["^You feel it welling back up from deep within you. Opening your mouth, the song pours forth. ","#","^narrator","/#","\n","ev","str","^Sing","/str","/ev",{"*":".^.c-0","flg":20},{"c-0":["\n",{"->":".^.^.^.loremaster_afraid"},{"#f":5}]}],{"loremaster_afraid":["^\"Wait, what are you-\" ","#","^loremaster ","/#","#","^minigame","/#","\n","ev",true,"/ev",{"VAR=":"essence_loremaster","re":true},{"->":".^.^.siren_sated_lore"},{"#f":1}],"siren_sated_lore":[["^The colour drains from her face and into your hands, filling you with a deep satisfaction. She turns and runs, stumbling in her haste to escape.","\n","^You ignore her, and gaze upon the new orb in your hands. ","#","^narrator","/#","\n","ev","str","^Admire prize","/str","/ev",{"*":".^.c-0","flg":20},{"c-0":["\n",{"->":"witch_day_four"},{"#f":5}]}],{"#f":1}],"#f":1}],"witch_day_four":[{"->":".^.witch_approach_day_4"},{"witch_approach_day_4":[["^You sense movement on the beach behind you. Glancing over your shoulder, you see the Witch steadily approaching the shoreline. With a sour hiss, you shift your scaled body further down the far side of the rock, warily peering at her through a small gap. ","#","^narration","/#","\n","ev","str","^Next","/str","/ev",{"*":".^.c-0","flg":20},{"c-0":["\n",{"->":".^.^.^.^.witch_approach_day_4_part2"},{"#f":5}]}],{"#f":1}],"witch_approach_day_4_part2":[["^She stops at the shoreline, looking in your direction with an unreadable expression on her beautiful face. She pulls a small, shiny object from her pocket, holding it to her heart as she begins to sing a tenuous melody, different from the previous day. ","#","^narration","/#","\n","ev","str","^Listen","/str","/ev",{"*":".^.c-0","flg":20},{"c-0":["\n",{"->":".^.^.^.^.witch_song_day_4"},{"#f":5}]}],{"#f":1}],"witch_song_day_4":[["^\"I’ll sing until the stars align,","\n","^And bring her back, forever mine.\" ","#","^witch","/#","\n","ev","str","^Next","/str","/ev",{"*":".^.c-0","flg":20},{"c-0":["\n",{"->":".^.^.^.^.witch_leaves_day_4"},{"#f":5}]}],{"#f":1}],"witch_leaves_day_4":[["^Upon finishing her brief song, the Witch leans down and gently places the item on a flat rock at the edge of the water. As she stands up, she looks in your direction once more. With a big sigh, she turns away and heads back to the village. ","#","^narration","/#","\n","ev","str","^Retreive item","/str","/ev",{"*":".^.c-0","flg":20},{"c-0":["\n","ev",true,"/ev",{"VAR=":"trinket_day_four","re":true},"#","^witch_song","/#","ev",true,"/ev",{"VAR=":"song_disgust","re":true},"end",{"#f":5}]}],{"#f":1}],"#f":1}],"global decl":["ev",false,{"VAR=":"essence_loremaster"},true,{"VAR=":"song_shipwrecking"},false,{"VAR=":"song_hope"},false,{"VAR=":"song_disgust"},false,{"VAR=":"trinket_day_three"},false,{"VAR=":"trinket_day_four"},false,{"VAR=":"teeth_done"},false,{"VAR=":"away_done"},"/ev","end",null],"#f":1}],"listDefs":{}}