<?xml version="1.0" encoding="UTF-8"?>
<objects serializationModel="Studio.02.02.00">
	<object class="MixerGroup" id="{75751f3a-1050-453a-b315-aa8cce04fe5e}">
		<property name="name">
			<value>Music</value>
		</property>
		<relationship name="effectChain">
			<destination>{abc79a71-54dd-444c-a7ff-82de97219f42}</destination>
		</relationship>
		<relationship name="panner">
			<destination>{1c41b3aa-bb85-4cf0-bd26-7141a86c74bf}</destination>
		</relationship>
		<relationship name="output">
			<destination>{94f793f5-9416-4e42-a27a-dc6ef61a55f3}</destination>
		</relationship>
	</object>
	<object class="MixerBusEffectChain" id="{abc79a71-54dd-444c-a7ff-82de97219f42}">
		<relationship name="effects">
			<destination>{a434216b-220a-4690-8fad-a689551a74ac}</destination>
			<destination>{3a47f8a9-0c41-4c7d-b00c-a6e41058203b}</destination>
		</relationship>
	</object>
	<object class="MixerBusPanner" id="{1c41b3aa-bb85-4cf0-bd26-7141a86c74bf}" />
	<object class="MixerBusFader" id="{a434216b-220a-4690-8fad-a689551a74ac}" />
	<object class="MixerSend" id="{3a47f8a9-0c41-4c7d-b00c-a6e41058203b}">
		<property name="level">
			<value>-20</value>
		</property>
		<property name="inputFormat">
			<value>1</value>
		</property>
		<relationship name="mixerReturn">
			<destination>{981d4edf-8b54-48b4-8163-7eb150f78c69}</destination>
		</relationship>
	</object>
</objects>
